{
  "2000": {
    "raw": "Summary:\n  Success rate:\t84.86%\n  Total:\t120.0017 secs\n  Slowest:\t59.2369 secs\n  Fastest:\t0.0014 secs\n  Average:\t25.4189 secs\n  Requests/sec:\t25.6330\n\n  Total data:\t7.52 KiB\n  Size/request:\t3 B\n  Size/sec:\t64 B\n\nResponse time histogram:\n   0.001 [1]    |\n   5.925 [1463] |\u25a0\u25a0\u25a0\u25a0\u25a0\u25a0\u25a0\u25a0\u25a0\u25a0\u25a0\u25a0\u25a0\u25a0\u25a0\u25a0\u25a0\u25a0\u25a0\u25a0\u25a0\u25a0\u25a0\u25a0\u25a0\u25a0\u25a0\u25a0\u25a0\u25a0\u25a0\u25a0\n  11.848 [0]    |\n  17.772 [0]    |\n  23.696 [0]    |\n  29.619 [0]    |\n  35.543 [0]    |\n  41.466 [0]    |\n  47.390 [0]    |\n  53.313 [0]    |\n  59.237 [1104] |\u25a0\u25a0\u25a0\u25a0\u25a0\u25a0\u25a0\u25a0\u25a0\u25a0\u25a0\u25a0\u25a0\u25a0\u25a0\u25a0\u25a0\u25a0\u25a0\u25a0\u25a0\u25a0\u25a0\u25a0\n\nResponse time distribution:\n  10.00% in 0.0033 secs\n  25.00% in 0.0047 secs\n  50.00% in 0.0292 secs\n  75.00% in 59.0833 secs\n  90.00% in 59.1598 secs\n  95.00% in 59.1757 secs\n  99.00% in 59.2105 secs\n  99.90% in 59.2360 secs\n  99.99% in 59.2369 secs\n\n\nDetails (average, fastest, slowest):\n  DNS+dialup:\t0.0002 secs, 0.0001 secs, 0.0005 secs\n  DNS-lookup:\t0.0000 secs, 0.0000 secs, 0.0001 secs\n\nStatus code distribution:\n  [200] 2568 responses\n\nError distribution:\n  [458] connection closed before message completed\n  [50] aborted due to deadline",
    "throughput": 25.633
  },
  "3000": {
    "raw": "Summary:\n  Success rate:\t84.74%\n  Total:\t120.0033 secs\n  Slowest:\t59.4683 secs\n  Fastest:\t0.0013 secs\n  Average:\t21.0217 secs\n  Requests/sec:\t25.4243\n\n  Total data:\t7.45 KiB\n  Size/request:\t3 B\n  Size/sec:\t63 B\n\nResponse time histogram:\n   0.001 [1]    |\n   5.948 [1643] |\u25a0\u25a0\u25a0\u25a0\u25a0\u25a0\u25a0\u25a0\u25a0\u25a0\u25a0\u25a0\u25a0\u25a0\u25a0\u25a0\u25a0\u25a0\u25a0\u25a0\u25a0\u25a0\u25a0\u25a0\u25a0\u25a0\u25a0\u25a0\u25a0\u25a0\u25a0\u25a0\n  11.895 [0]    |\n  17.841 [0]    |\n  23.788 [0]    |\n  29.735 [0]    |\n  35.681 [0]    |\n  41.628 [0]    |\n  47.575 [0]    |\n  53.522 [0]    |\n  59.468 [899]  |\u25a0\u25a0\u25a0\u25a0\u25a0\u25a0\u25a0\u25a0\u25a0\u25a0\u25a0\u25a0\u25a0\u25a0\u25a0\u25a0\u25a0\n\nResponse time distribution:\n  10.00% in 0.0035 secs\n  25.00% in 0.0085 secs\n  50.00% in 0.0451 secs\n  75.00% in 59.4085 secs\n  90.00% in 59.4209 secs\n  95.00% in 59.4266 secs\n  99.00% in 59.4583 secs\n  99.90% in 59.4652 secs\n  99.99% in 59.4683 secs\n\n\nDetails (average, fastest, slowest):\n  DNS+dialup:\t0.0002 secs, 0.0001 secs, 0.0007 secs\n  DNS-lookup:\t0.0000 secs, 0.0000 secs, 0.0002 secs\n\nStatus code distribution:\n  [200] 2543 responses\n\nError distribution:\n  [458] connection closed before message completed\n  [50] aborted due to deadline",
    "throughput": 25.4243
  },
  "4000": {
    "raw": "Summary:\n  Success rate:\t84.52%\n  Total:\t120.0032 secs\n  Slowest:\t59.7717 secs\n  Fastest:\t0.0035 secs\n  Average:\t23.8988 secs\n  Requests/sec:\t25.0743\n\n  Total data:\t7.33 KiB\n  Size/request:\t3 B\n  Size/sec:\t62 B\n\nResponse time histogram:\n   0.004 [1]    |\n   5.980 [1502] |\u25a0\u25a0\u25a0\u25a0\u25a0\u25a0\u25a0\u25a0\u25a0\u25a0\u25a0\u25a0\u25a0\u25a0\u25a0\u25a0\u25a0\u25a0\u25a0\u25a0\u25a0\u25a0\u25a0\u25a0\u25a0\u25a0\u25a0\u25a0\u25a0\u25a0\u25a0\u25a0\n  11.957 [0]    |\n  17.934 [0]    |\n  23.911 [0]    |\n  29.888 [0]    |\n  35.864 [0]    |\n  41.841 [0]    |\n  47.818 [0]    |\n  53.795 [0]    |\n  59.772 [998]  |\u25a0\u25a0\u25a0\u25a0\u25a0\u25a0\u25a0\u25a0\u25a0\u25a0\u25a0\u25a0\u25a0\u25a0\u25a0\u25a0\u25a0\u25a0\u25a0\u25a0\u25a0\n\nResponse time distribution:\n  10.00% in 0.0850 secs\n  25.00% in 0.1072 secs\n  50.00% in 0.1393 secs\n  75.00% in 59.7216 secs\n  90.00% in 59.7348 secs\n  95.00% in 59.7372 secs\n  99.00% in 59.7620 secs\n  99.90% in 59.7704 secs\n  99.99% in 59.7717 secs\n\n\nDetails (average, fastest, slowest):\n  DNS+dialup:\t0.0002 secs, 0.0001 secs, 0.0006 secs\n  DNS-lookup:\t0.0000 secs, 0.0000 secs, 0.0002 secs\n\nStatus code distribution:\n  [200] 2501 responses\n\nError distribution:\n  [458] connection closed before message completed\n  [50] aborted due to deadline",
    "throughput": 25.0743
  },
  "4500": {
    "raw": "Summary:\n  Success rate:\t85.65%\n  Total:\t120.0043 secs\n  Slowest:\t59.8465 secs\n  Fastest:\t0.0027 secs\n  Average:\t26.6290 secs\n  Requests/sec:\t27.0157\n\n  Total data:\t8.01 KiB\n  Size/request:\t3 B\n  Size/sec:\t68 B\n\nResponse time histogram:\n   0.003 [1]    |\n   5.987 [1518] |\u25a0\u25a0\u25a0\u25a0\u25a0\u25a0\u25a0\u25a0\u25a0\u25a0\u25a0\u25a0\u25a0\u25a0\u25a0\u25a0\u25a0\u25a0\u25a0\u25a0\u25a0\u25a0\u25a0\u25a0\u25a0\u25a0\u25a0\u25a0\u25a0\u25a0\u25a0\u25a0\n  11.971 [0]    |\n  17.956 [0]    |\n  23.940 [0]    |\n  29.925 [0]    |\n  35.909 [0]    |\n  41.893 [0]    |\n  47.878 [0]    |\n  53.862 [0]    |\n  59.847 [1215] |\u25a0\u25a0\u25a0\u25a0\u25a0\u25a0\u25a0\u25a0\u25a0\u25a0\u25a0\u25a0\u25a0\u25a0\u25a0\u25a0\u25a0\u25a0\u25a0\u25a0\u25a0\u25a0\u25a0\u25a0\u25a0\n\nResponse time distribution:\n  10.00% in 0.1018 secs\n  25.00% in 0.1120 secs\n  50.00% in 0.1358 secs\n  75.00% in 59.7858 secs\n  90.00% in 59.7961 secs\n  95.00% in 59.8012 secs\n  99.00% in 59.8218 secs\n  99.90% in 59.8322 secs\n  99.99% in 59.8465 secs\n\n\nDetails (average, fastest, slowest):\n  DNS+dialup:\t0.0002 secs, 0.0001 secs, 0.0006 secs\n  DNS-lookup:\t0.0000 secs, 0.0000 secs, 0.0001 secs\n\nStatus code distribution:\n  [200] 2734 responses\n\nError distribution:\n  [458] connection closed before message completed\n  [50] aborted due to deadline",
    "throughput": 27.0157
  },
  "5000": {
    "raw": "Summary:\n  Success rate:\t84.35%\n  Total:\t120.0038 secs\n  Slowest:\t59.8486 secs\n  Fastest:\t0.0048 secs\n  Average:\t16.7867 secs\n  Requests/sec:\t24.7992\n\n  Total data:\t7.23 KiB\n  Size/request:\t3 B\n  Size/sec:\t61 B\n\nResponse time histogram:\n   0.005 [1]    |\n   5.989 [1778] |\u25a0\u25a0\u25a0\u25a0\u25a0\u25a0\u25a0\u25a0\u25a0\u25a0\u25a0\u25a0\u25a0\u25a0\u25a0\u25a0\u25a0\u25a0\u25a0\u25a0\u25a0\u25a0\u25a0\u25a0\u25a0\u25a0\u25a0\u25a0\u25a0\u25a0\u25a0\u25a0\n  11.974 [0]    |\n  17.958 [0]    |\n  23.942 [0]    |\n  29.927 [0]    |\n  35.911 [0]    |\n  41.895 [0]    |\n  47.880 [0]    |\n  53.864 [0]    |\n  59.849 [689]  |\u25a0\u25a0\u25a0\u25a0\u25a0\u25a0\u25a0\u25a0\u25a0\u25a0\u25a0\u25a0\n\nResponse time distribution:\n  10.00% in 0.1033 secs\n  25.00% in 0.1156 secs\n  50.00% in 0.1279 secs\n  75.00% in 59.6889 secs\n  90.00% in 59.8184 secs\n  95.00% in 59.8233 secs\n  99.00% in 59.8386 secs\n  99.90% in 59.8459 secs\n  99.99% in 59.8486 secs\n\n\nDetails (average, fastest, slowest):\n  DNS+dialup:\t0.0002 secs, 0.0001 secs, 0.0008 secs\n  DNS-lookup:\t0.0000 secs, 0.0000 secs, 0.0001 secs\n\nStatus code distribution:\n  [200] 2468 responses\n\nError distribution:\n  [458] connection closed before message completed\n  [50] aborted due to deadline",
    "throughput": 24.7992
  },
  "5500": {
    "raw": "Summary:\n  Success rate:\t84.05%\n  Total:\t120.0044 secs\n  Slowest:\t59.9768 secs\n  Fastest:\t0.0023 secs\n  Average:\t23.8687 secs\n  Requests/sec:\t24.3491\n\n  Total data:\t7.07 KiB\n  Size/request:\t3 B\n  Size/sec:\t60 B\n\nResponse time histogram:\n   0.002 [1]    |\n   6.000 [1455] |\u25a0\u25a0\u25a0\u25a0\u25a0\u25a0\u25a0\u25a0\u25a0\u25a0\u25a0\u25a0\u25a0\u25a0\u25a0\u25a0\u25a0\u25a0\u25a0\u25a0\u25a0\u25a0\u25a0\u25a0\u25a0\u25a0\u25a0\u25a0\u25a0\u25a0\u25a0\u25a0\n  11.997 [0]    |\n  17.995 [0]    |\n  23.992 [0]    |\n  29.990 [0]    |\n  35.987 [0]    |\n  41.984 [0]    |\n  47.982 [0]    |\n  53.979 [0]    |\n  59.977 [958]  |\u25a0\u25a0\u25a0\u25a0\u25a0\u25a0\u25a0\u25a0\u25a0\u25a0\u25a0\u25a0\u25a0\u25a0\u25a0\u25a0\u25a0\u25a0\u25a0\u25a0\u25a0\n\nResponse time distribution:\n  10.00% in 0.0941 secs\n  25.00% in 0.1664 secs\n  50.00% in 0.2200 secs\n  75.00% in 59.8836 secs\n  90.00% in 59.9316 secs\n  95.00% in 59.9449 secs\n  99.00% in 59.9570 secs\n  99.90% in 59.9740 secs\n  99.99% in 59.9768 secs\n\n\nDetails (average, fastest, slowest):\n  DNS+dialup:\t0.0002 secs, 0.0001 secs, 0.0006 secs\n  DNS-lookup:\t0.0000 secs, 0.0000 secs, 0.0001 secs\n\nStatus code distribution:\n  [200] 2414 responses\n\nError distribution:\n  [458] connection closed before message completed\n  [50] aborted due to deadline",
    "throughput": 24.3491
  },
  "6000": {
    "raw": "Summary:\n  Success rate:\t86.64%\n  Total:\t120.0039 secs\n  Slowest:\t59.9531 secs\n  Fastest:\t0.0039 secs\n  Average:\t16.1726 secs\n  Requests/sec:\t28.9824\n\n  Total data:\t8.70 KiB\n  Size/request:\t3 B\n  Size/sec:\t74 B\n\nResponse time histogram:\n   0.004 [1]    |\n   5.999 [2175] |\u25a0\u25a0\u25a0\u25a0\u25a0\u25a0\u25a0\u25a0\u25a0\u25a0\u25a0\u25a0\u25a0\u25a0\u25a0\u25a0\u25a0\u25a0\u25a0\u25a0\u25a0\u25a0\u25a0\u25a0\u25a0\u25a0\u25a0\u25a0\u25a0\u25a0\u25a0\u25a0\n  11.994 [0]    |\n  17.989 [0]    |\n  23.984 [0]    |\n  29.979 [0]    |\n  35.973 [0]    |\n  41.968 [0]    |\n  47.963 [0]    |\n  53.958 [0]    |\n  59.953 [794]  |\u25a0\u25a0\u25a0\u25a0\u25a0\u25a0\u25a0\u25a0\u25a0\u25a0\u25a0\n\nResponse time distribution:\n  10.00% in 0.1106 secs\n  25.00% in 0.2454 secs\n  50.00% in 0.2854 secs\n  75.00% in 59.7082 secs\n  90.00% in 59.8868 secs\n  95.00% in 59.9170 secs\n  99.00% in 59.9316 secs\n  99.90% in 59.9488 secs\n  99.99% in 59.9531 secs\n\n\nDetails (average, fastest, slowest):\n  DNS+dialup:\t0.0002 secs, 0.0001 secs, 0.0018 secs\n  DNS-lookup:\t0.0000 secs, 0.0000 secs, 0.0002 secs\n\nStatus code distribution:\n  [200] 2970 responses\n\nError distribution:\n  [458] connection closed before message completed\n  [50] aborted due to deadline",
    "throughput": 28.9824
  }
}