{
  "2000": {
    "raw": "Summary:\n  Success rate:\t100.00%\n  Total:\t120.0024 secs\n  Slowest:\t48.0088 secs\n  Fastest:\t0.0011 secs\n  Average:\t8.0982 secs\n  Requests/sec:\t1349.7566\n\n  Total data:\t474.40 KiB\n  Size/request:\t3 B\n  Size/sec:\t3.95 KiB\n\nResponse time histogram:\n   0.001 [1]      |\n   4.802 [131591] |\u25a0\u25a0\u25a0\u25a0\u25a0\u25a0\u25a0\u25a0\u25a0\u25a0\u25a0\u25a0\u25a0\u25a0\u25a0\u25a0\u25a0\u25a0\u25a0\u25a0\u25a0\u25a0\u25a0\u25a0\u25a0\u25a0\u25a0\u25a0\u25a0\u25a0\u25a0\u25a0\n   9.603 [150]    |\n  14.403 [62]     |\n  19.204 [6]      |\n  24.005 [0]      |\n  28.806 [0]      |\n  33.606 [0]      |\n  38.407 [0]      |\n  43.208 [14009]  |\u25a0\u25a0\u25a0\n  48.009 [16111]  |\u25a0\u25a0\u25a0\n\nResponse time distribution:\n  10.00% in 0.0026 secs\n  25.00% in 0.0038 secs\n  50.00% in 0.0058 secs\n  75.00% in 0.0222 secs\n  90.00% in 43.1820 secs\n  95.00% in 45.4641 secs\n  99.00% in 47.2993 secs\n  99.90% in 47.7214 secs\n  99.99% in 47.9396 secs\n\n\nDetails (average, fastest, slowest):\n  DNS+dialup:\t0.0003 secs, 0.0002 secs, 0.0006 secs\n  DNS-lookup:\t0.0000 secs, 0.0000 secs, 0.0001 secs\n\nStatus code distribution:\n  [200] 161930 responses\n\nError distribution:\n  [44] aborted due to deadline",
    "throughput": 1349.7566,
    "hit_rate": {}
  },
  "3000": {
    "raw": "Summary:\n  Success rate:\t100.00%\n  Total:\t120.0023 secs\n  Slowest:\t72.8534 secs\n  Fastest:\t0.0011 secs\n  Average:\t5.3670 secs\n  Requests/sec:\t1214.5599\n\n  Total data:\t426.86 KiB\n  Size/request:\t3 B\n  Size/sec:\t3.56 KiB\n\nResponse time histogram:\n   0.001 [1]      |\n   7.286 [134843] |\u25a0\u25a0\u25a0\u25a0\u25a0\u25a0\u25a0\u25a0\u25a0\u25a0\u25a0\u25a0\u25a0\u25a0\u25a0\u25a0\u25a0\u25a0\u25a0\u25a0\u25a0\u25a0\u25a0\u25a0\u25a0\u25a0\u25a0\u25a0\u25a0\u25a0\u25a0\u25a0\n  14.572 [42]     |\n  21.857 [14]     |\n  29.142 [0]      |\n  36.427 [0]      |\n  43.712 [0]      |\n  50.998 [0]      |\n  58.283 [0]      |\n  65.568 [0]      |\n  72.853 [10802]  |\u25a0\u25a0\n\nResponse time distribution:\n  10.00% in 0.0023 secs\n  25.00% in 0.0037 secs\n  50.00% in 0.0065 secs\n  75.00% in 0.0167 secs\n  90.00% in 0.0784 secs\n  95.00% in 71.8903 secs\n  99.00% in 72.5671 secs\n  99.90% in 72.7163 secs\n  99.99% in 72.8175 secs\n\n\nDetails (average, fastest, slowest):\n  DNS+dialup:\t0.0003 secs, 0.0001 secs, 0.0006 secs\n  DNS-lookup:\t0.0000 secs, 0.0000 secs, 0.0002 secs\n\nStatus code distribution:\n  [200] 145702 responses\n\nError distribution:\n  [48] aborted due to deadline",
    "throughput": 1214.5599,
    "hit_rate": {}
  },
  "4000": {
    "raw": "Summary:\n  Success rate:\t100.00%\n  Total:\t120.0020 secs\n  Slowest:\t81.2203 secs\n  Fastest:\t0.0034 secs\n  Average:\t13.7211 secs\n  Requests/sec:\t1336.0527\n\n  Total data:\t469.58 KiB\n  Size/request:\t3 B\n  Size/sec:\t3.91 KiB\n\nResponse time histogram:\n   0.003 [1]      |\n   8.125 [133450] |\u25a0\u25a0\u25a0\u25a0\u25a0\u25a0\u25a0\u25a0\u25a0\u25a0\u25a0\u25a0\u25a0\u25a0\u25a0\u25a0\u25a0\u25a0\u25a0\u25a0\u25a0\u25a0\u25a0\u25a0\u25a0\u25a0\u25a0\u25a0\u25a0\u25a0\u25a0\u25a0\n  16.247 [91]     |\n  24.369 [5]      |\n  32.490 [19]     |\n  40.612 [0]      |\n  48.734 [0]      |\n  56.855 [0]      |\n  64.977 [0]      |\n  73.099 [0]      |\n  81.220 [26717]  |\u25a0\u25a0\u25a0\u25a0\u25a0\u25a0\n\nResponse time distribution:\n  10.00% in 0.2579 secs\n  25.00% in 0.3022 secs\n  50.00% in 0.3525 secs\n  75.00% in 0.3924 secs\n  90.00% in 80.4075 secs\n  95.00% in 80.7523 secs\n  99.00% in 81.0614 secs\n  99.90% in 81.1168 secs\n  99.99% in 81.1850 secs\n\n\nDetails (average, fastest, slowest):\n  DNS+dialup:\t0.0003 secs, 0.0001 secs, 0.0008 secs\n  DNS-lookup:\t0.0000 secs, 0.0000 secs, 0.0001 secs\n\nStatus code distribution:\n  [200] 160283 responses\n\nError distribution:\n  [46] aborted due to deadline",
    "throughput": 1336.0527,
    "hit_rate": {}
  },
  "4500": {
    "raw": "Summary:\n  Success rate:\t100.00%\n  Total:\t120.0034 secs\n  Slowest:\t19.7202 secs\n  Fastest:\t0.0033 secs\n  Average:\t2.4400 secs\n  Requests/sec:\t1114.7014\n\n  Total data:\t391.75 KiB\n  Size/request:\t3 B\n  Size/sec:\t3.26 KiB\n\nResponse time histogram:\n   0.003 [1]     |\n   1.975 [53897] |\u25a0\u25a0\u25a0\u25a0\u25a0\u25a0\u25a0\u25a0\u25a0\u25a0\u25a0\u25a0\u25a0\u25a0\u25a0\u25a0\u25a0\u25a0\u25a0\u25a0\u25a0\u25a0\u25a0\u25a0\u25a0\u25a0\u25a0\u25a0\u25a0\n   3.947 [58394] |\u25a0\u25a0\u25a0\u25a0\u25a0\u25a0\u25a0\u25a0\u25a0\u25a0\u25a0\u25a0\u25a0\u25a0\u25a0\u25a0\u25a0\u25a0\u25a0\u25a0\u25a0\u25a0\u25a0\u25a0\u25a0\u25a0\u25a0\u25a0\u25a0\u25a0\u25a0\u25a0\n   5.918 [21310] |\u25a0\u25a0\u25a0\u25a0\u25a0\u25a0\u25a0\u25a0\u25a0\u25a0\u25a0\n   7.890 [0]     |\n   9.862 [74]    |\n  11.833 [3]     |\n  13.805 [0]     |\n  15.777 [37]    |\n  17.749 [0]     |\n  19.720 [2]     |\n\nResponse time distribution:\n  10.00% in 0.6369 secs\n  25.00% in 1.2463 secs\n  50.00% in 2.4211 secs\n  75.00% in 3.6504 secs\n  90.00% in 4.2846 secs\n  95.00% in 4.4917 secs\n  99.00% in 4.7189 secs\n  99.90% in 4.9034 secs\n  99.99% in 14.8432 secs\n\n\nDetails (average, fastest, slowest):\n  DNS+dialup:\t0.0003 secs, 0.0001 secs, 0.0006 secs\n  DNS-lookup:\t0.0000 secs, 0.0000 secs, 0.0001 secs\n\nStatus code distribution:\n  [200] 133718 responses\n\nError distribution:\n  [50] aborted due to deadline",
    "throughput": 1114.7014,
    "hit_rate": {}
  },
  "5000": {
    "raw": "Summary:\n  Success rate:\t100.00%\n  Total:\t120.0046 secs\n  Slowest:\t89.7466 secs\n  Fastest:\t0.0288 secs\n  Average:\t13.2679 secs\n  Requests/sec:\t1263.0932\n\n  Total data:\t443.93 KiB\n  Size/request:\t3 B\n  Size/sec:\t3.70 KiB\n\nResponse time histogram:\n   0.029 [1]      |\n   9.001 [134509] |\u25a0\u25a0\u25a0\u25a0\u25a0\u25a0\u25a0\u25a0\u25a0\u25a0\u25a0\u25a0\u25a0\u25a0\u25a0\u25a0\u25a0\u25a0\u25a0\u25a0\u25a0\u25a0\u25a0\u25a0\u25a0\u25a0\u25a0\u25a0\u25a0\u25a0\u25a0\u25a0\n  17.972 [188]    |\n  26.944 [194]    |\n  35.916 [11]     |\n  44.888 [0]      |\n  53.860 [0]      |\n  62.831 [0]      |\n  71.803 [0]      |\n  80.775 [0]      |\n  89.747 [16626]  |\u25a0\u25a0\u25a0\n\nResponse time distribution:\n  10.00% in 1.1983 secs\n  25.00% in 2.4423 secs\n  50.00% in 4.1491 secs\n  75.00% in 6.2216 secs\n  90.00% in 89.4419 secs\n  95.00% in 89.6043 secs\n  99.00% in 89.6665 secs\n  99.90% in 89.6950 secs\n  99.99% in 89.7179 secs\n\n\nDetails (average, fastest, slowest):\n  DNS+dialup:\t0.0003 secs, 0.0001 secs, 0.0006 secs\n  DNS-lookup:\t0.0000 secs, 0.0000 secs, 0.0001 secs\n\nStatus code distribution:\n  [200] 151529 responses\n\nError distribution:\n  [48] aborted due to deadline",
    "throughput": 1263.0932,
    "hit_rate": {}
  },
  "5500": {
    "raw": "Summary:\n  Success rate:\t100.00%\n  Total:\t120.0046 secs\n  Slowest:\t25.7155 secs\n  Fastest:\t0.0039 secs\n  Average:\t5.1401 secs\n  Requests/sec:\t1106.7910\n\n  Total data:\t388.97 KiB\n  Size/request:\t3 B\n  Size/sec:\t3.24 KiB\n\nResponse time histogram:\n   0.004 [1]     |\n   2.575 [31187] |\u25a0\u25a0\u25a0\u25a0\u25a0\u25a0\u25a0\u25a0\u25a0\u25a0\u25a0\u25a0\u25a0\u25a0\u25a0\u25a0\u25a0\u25a0\u25a0\u25a0\u25a0\u25a0\u25a0\u25a0\u25a0\u25a0\u25a0\n   5.146 [35367] |\u25a0\u25a0\u25a0\u25a0\u25a0\u25a0\u25a0\u25a0\u25a0\u25a0\u25a0\u25a0\u25a0\u25a0\u25a0\u25a0\u25a0\u25a0\u25a0\u25a0\u25a0\u25a0\u25a0\u25a0\u25a0\u25a0\u25a0\u25a0\u25a0\u25a0\u25a0\n   7.717 [35697] |\u25a0\u25a0\u25a0\u25a0\u25a0\u25a0\u25a0\u25a0\u25a0\u25a0\u25a0\u25a0\u25a0\u25a0\u25a0\u25a0\u25a0\u25a0\u25a0\u25a0\u25a0\u25a0\u25a0\u25a0\u25a0\u25a0\u25a0\u25a0\u25a0\u25a0\u25a0\u25a0\n  10.289 [29931] |\u25a0\u25a0\u25a0\u25a0\u25a0\u25a0\u25a0\u25a0\u25a0\u25a0\u25a0\u25a0\u25a0\u25a0\u25a0\u25a0\u25a0\u25a0\u25a0\u25a0\u25a0\u25a0\u25a0\u25a0\u25a0\u25a0\n  12.860 [327]   |\n  15.431 [161]   |\n  18.002 [17]    |\n  20.573 [59]    |\n  23.144 [0]     |\n  25.716 [23]    |\n\nResponse time distribution:\n  10.00% in 1.1731 secs\n  25.00% in 2.7318 secs\n  50.00% in 5.1324 secs\n  75.00% in 7.5867 secs\n  90.00% in 8.9525 secs\n  95.00% in 9.3879 secs\n  99.00% in 10.0936 secs\n  99.90% in 15.3722 secs\n  99.99% in 25.6041 secs\n\n\nDetails (average, fastest, slowest):\n  DNS+dialup:\t0.0003 secs, 0.0001 secs, 0.0005 secs\n  DNS-lookup:\t0.0000 secs, 0.0000 secs, 0.0001 secs\n\nStatus code distribution:\n  [200] 132770 responses\n\nError distribution:\n  [50] aborted due to deadline",
    "throughput": 1106.791,
    "hit_rate": {}
  },
  "6000": {
    "raw": "Summary:\n  Success rate:\t100.00%\n  Total:\t120.0037 secs\n  Slowest:\t32.5916 secs\n  Fastest:\t0.0367 secs\n  Average:\t6.0583 secs\n  Requests/sec:\t1115.4321\n\n  Total data:\t392.01 KiB\n  Size/request:\t3 B\n  Size/sec:\t3.27 KiB\n\nResponse time histogram:\n   0.037 [1]     |\n   3.292 [33446] |\u25a0\u25a0\u25a0\u25a0\u25a0\u25a0\u25a0\u25a0\u25a0\u25a0\u25a0\u25a0\u25a0\u25a0\u25a0\u25a0\u25a0\u25a0\u25a0\u25a0\u25a0\u25a0\u25a0\u25a0\u25a0\u25a0\n   6.548 [39301] |\u25a0\u25a0\u25a0\u25a0\u25a0\u25a0\u25a0\u25a0\u25a0\u25a0\u25a0\u25a0\u25a0\u25a0\u25a0\u25a0\u25a0\u25a0\u25a0\u25a0\u25a0\u25a0\u25a0\u25a0\u25a0\u25a0\u25a0\u25a0\u25a0\u25a0\u25a0\n   9.803 [40180] |\u25a0\u25a0\u25a0\u25a0\u25a0\u25a0\u25a0\u25a0\u25a0\u25a0\u25a0\u25a0\u25a0\u25a0\u25a0\u25a0\u25a0\u25a0\u25a0\u25a0\u25a0\u25a0\u25a0\u25a0\u25a0\u25a0\u25a0\u25a0\u25a0\u25a0\u25a0\u25a0\n  13.059 [20647] |\u25a0\u25a0\u25a0\u25a0\u25a0\u25a0\u25a0\u25a0\u25a0\u25a0\u25a0\u25a0\u25a0\u25a0\u25a0\u25a0\n  16.314 [0]     |\n  19.570 [179]   |\n  22.825 [20]    |\n  26.081 [0]     |\n  29.336 [8]     |\n  32.592 [24]    |\n\nResponse time distribution:\n  10.00% in 1.4746 secs\n  25.00% in 3.2927 secs\n  50.00% in 6.0652 secs\n  75.00% in 8.8657 secs\n  90.00% in 10.4345 secs\n  95.00% in 10.9714 secs\n  99.00% in 12.0029 secs\n  99.90% in 17.2786 secs\n  99.99% in 32.4780 secs\n\n\nDetails (average, fastest, slowest):\n  DNS+dialup:\t0.0003 secs, 0.0001 secs, 0.0006 secs\n  DNS-lookup:\t0.0000 secs, 0.0000 secs, 0.0001 secs\n\nStatus code distribution:\n  [200] 133806 responses\n\nError distribution:\n  [50] aborted due to deadline",
    "throughput": 1115.4321,
    "hit_rate": {}
  }
}