{
  "500": {
    "raw": "Summary:\n  Success rate:\t100.00%\n  Total:\t30.0020 secs\n  Slowest:\t0.2618 secs\n  Fastest:\t0.0066 secs\n  Average:\t0.0119 secs\n  Requests/sec:\t500.0005\n\n  Total data:\t117.15 KiB\n  Size/request:\t8 B\n  Size/sec:\t3.90 KiB\n\nResponse time histogram:\n  0.007 [1]     |\n  0.032 [14865] |\u25a0\u25a0\u25a0\u25a0\u25a0\u25a0\u25a0\u25a0\u25a0\u25a0\u25a0\u25a0\u25a0\u25a0\u25a0\u25a0\u25a0\u25a0\u25a0\u25a0\u25a0\u25a0\u25a0\u25a0\u25a0\u25a0\u25a0\u25a0\u25a0\u25a0\u25a0\u25a0\n  0.058 [15]    |\n  0.083 [13]    |\n  0.109 [13]    |\n  0.134 [15]    |\n  0.160 [16]    |\n  0.185 [18]    |\n  0.211 [12]    |\n  0.236 [13]    |\n  0.262 [14]    |\n\nResponse time distribution:\n  10.00% in 0.0100 secs\n  25.00% in 0.0103 secs\n  50.00% in 0.0106 secs\n  75.00% in 0.0110 secs\n  90.00% in 0.0116 secs\n  95.00% in 0.0121 secs\n  99.00% in 0.0159 secs\n  99.90% in 0.2363 secs\n  99.99% in 0.2584 secs\n\n\nDetails (average, fastest, slowest):\n  DNS+dialup:\t0.0003 secs, 0.0001 secs, 0.0009 secs\n  DNS-lookup:\t0.0000 secs, 0.0000 secs, 0.0004 secs\n\nStatus code distribution:\n  [200] 14995 responses\n\nError distribution:\n  [6] aborted due to deadline",
    "throughput": 500.0005
  },
  "1000": {
    "raw": "Summary:\n  Success rate:\t100.00%\n  Total:\t30.0014 secs\n  Slowest:\t0.2424 secs\n  Fastest:\t0.0054 secs\n  Average:\t0.0103 secs\n  Requests/sec:\t1000.0210\n\n  Total data:\t234.31 KiB\n  Size/request:\t8 B\n  Size/sec:\t7.81 KiB\n\nResponse time histogram:\n  0.005 [1]     |\n  0.029 [29725] |\u25a0\u25a0\u25a0\u25a0\u25a0\u25a0\u25a0\u25a0\u25a0\u25a0\u25a0\u25a0\u25a0\u25a0\u25a0\u25a0\u25a0\u25a0\u25a0\u25a0\u25a0\u25a0\u25a0\u25a0\u25a0\u25a0\u25a0\u25a0\u25a0\u25a0\u25a0\u25a0\n  0.053 [28]    |\n  0.076 [33]    |\n  0.100 [27]    |\n  0.124 [34]    |\n  0.148 [32]    |\n  0.171 [32]    |\n  0.195 [42]    |\n  0.219 [25]    |\n  0.242 [13]    |\n\nResponse time distribution:\n  10.00% in 0.0082 secs\n  25.00% in 0.0086 secs\n  50.00% in 0.0090 secs\n  75.00% in 0.0096 secs\n  90.00% in 0.0104 secs\n  95.00% in 0.0112 secs\n  99.00% in 0.0159 secs\n  99.90% in 0.1978 secs\n  99.99% in 0.2350 secs\n\n\nDetails (average, fastest, slowest):\n  DNS+dialup:\t0.0003 secs, 0.0001 secs, 0.0017 secs\n  DNS-lookup:\t0.0000 secs, 0.0000 secs, 0.0004 secs\n\nStatus code distribution:\n  [200] 29992 responses\n\nError distribution:\n  [10] aborted due to deadline",
    "throughput": 1000.021
  },
  "1500": {
    "raw": "Summary:\n  Success rate:\t100.00%\n  Total:\t30.0018 secs\n  Slowest:\t0.2669 secs\n  Fastest:\t0.0050 secs\n  Average:\t0.0102 secs\n  Requests/sec:\t1499.8453\n\n  Total data:\t351.48 KiB\n  Size/request:\t8 B\n  Size/sec:\t11.71 KiB\n\nResponse time histogram:\n  0.005 [1]     |\n  0.031 [44439] |\u25a0\u25a0\u25a0\u25a0\u25a0\u25a0\u25a0\u25a0\u25a0\u25a0\u25a0\u25a0\u25a0\u25a0\u25a0\u25a0\u25a0\u25a0\u25a0\u25a0\u25a0\u25a0\u25a0\u25a0\u25a0\u25a0\u25a0\u25a0\u25a0\u25a0\u25a0\u25a0\n  0.057 [81]    |\n  0.084 [54]    |\n  0.110 [60]    |\n  0.136 [52]    |\n  0.162 [66]    |\n  0.188 [65]    |\n  0.215 [68]    |\n  0.241 [71]    |\n  0.267 [33]    |\n\nResponse time distribution:\n  10.00% in 0.0074 secs\n  25.00% in 0.0078 secs\n  50.00% in 0.0083 secs\n  75.00% in 0.0090 secs\n  90.00% in 0.0100 secs\n  95.00% in 0.0110 secs\n  99.00% in 0.0685 secs\n  99.90% in 0.2330 secs\n  99.99% in 0.2621 secs\n\n\nDetails (average, fastest, slowest):\n  DNS+dialup:\t0.0003 secs, 0.0001 secs, 0.0068 secs\n  DNS-lookup:\t0.0000 secs, 0.0000 secs, 0.0005 secs\n\nStatus code distribution:\n  [200] 44990 responses\n\nError distribution:\n  [8] aborted due to deadline",
    "throughput": 1499.8453
  },
  "2000": {
    "raw": "Summary:\n  Success rate:\t100.00%\n  Total:\t30.0018 secs\n  Slowest:\t0.3275 secs\n  Fastest:\t0.0050 secs\n  Average:\t0.0113 secs\n  Requests/sec:\t1999.8126\n\n  Total data:\t468.65 KiB\n  Size/request:\t8 B\n  Size/sec:\t15.62 KiB\n\nResponse time histogram:\n  0.005 [1]     |\n  0.037 [58877] |\u25a0\u25a0\u25a0\u25a0\u25a0\u25a0\u25a0\u25a0\u25a0\u25a0\u25a0\u25a0\u25a0\u25a0\u25a0\u25a0\u25a0\u25a0\u25a0\u25a0\u25a0\u25a0\u25a0\u25a0\u25a0\u25a0\u25a0\u25a0\u25a0\u25a0\u25a0\u25a0\n  0.069 [179]   |\n  0.102 [114]   |\n  0.134 [102]   |\n  0.166 [111]   |\n  0.198 [114]   |\n  0.231 [112]   |\n  0.263 [112]   |\n  0.295 [129]   |\n  0.327 [136]   |\n\nResponse time distribution:\n  10.00% in 0.0068 secs\n  25.00% in 0.0072 secs\n  50.00% in 0.0078 secs\n  75.00% in 0.0086 secs\n  90.00% in 0.0099 secs\n  95.00% in 0.0112 secs\n  99.00% in 0.1678 secs\n  99.90% in 0.3064 secs\n  99.99% in 0.3233 secs\n\n\nDetails (average, fastest, slowest):\n  DNS+dialup:\t0.0003 secs, 0.0001 secs, 0.0060 secs\n  DNS-lookup:\t0.0000 secs, 0.0000 secs, 0.0005 secs\n\nStatus code distribution:\n  [200] 59987 responses\n\nError distribution:\n  [11] aborted due to deadline",
    "throughput": 1999.8126
  },
  "2500": {
    "raw": "Summary:\n  Success rate:\t100.00%\n  Total:\t30.0020 secs\n  Slowest:\t1.0278 secs\n  Fastest:\t0.0053 secs\n  Average:\t0.0102 secs\n  Requests/sec:\t2499.7707\n\n  Total data:\t585.78 KiB\n  Size/request:\t8 B\n  Size/sec:\t19.52 KiB\n\nResponse time histogram:\n  0.005 [1]     |\n  0.108 [74096] |\u25a0\u25a0\u25a0\u25a0\u25a0\u25a0\u25a0\u25a0\u25a0\u25a0\u25a0\u25a0\u25a0\u25a0\u25a0\u25a0\u25a0\u25a0\u25a0\u25a0\u25a0\u25a0\u25a0\u25a0\u25a0\u25a0\u25a0\u25a0\u25a0\u25a0\u25a0\u25a0\n  0.210 [840]   |\n  0.312 [41]    |\n  0.414 [0]     |\n  0.517 [0]     |\n  0.619 [0]     |\n  0.721 [0]     |\n  0.823 [0]     |\n  0.926 [0]     |\n  1.028 [2]     |\n\nResponse time distribution:\n  10.00% in 0.0065 secs\n  25.00% in 0.0069 secs\n  50.00% in 0.0075 secs\n  75.00% in 0.0085 secs\n  90.00% in 0.0100 secs\n  95.00% in 0.0113 secs\n  99.00% in 0.1321 secs\n  99.90% in 0.2064 secs\n  99.99% in 0.2182 secs\n\n\nDetails (average, fastest, slowest):\n  DNS+dialup:\t0.0003 secs, 0.0001 secs, 1.0210 secs\n  DNS-lookup:\t0.0000 secs, 0.0000 secs, 0.0005 secs\n\nStatus code distribution:\n  [200] 74980 responses\n\nError distribution:\n  [18] aborted due to deadline",
    "throughput": 2499.7707
  },
  "3000": {
    "raw": "Summary:\n  Success rate:\t100.00%\n  Total:\t30.0017 secs\n  Slowest:\t0.2162 secs\n  Fastest:\t0.0048 secs\n  Average:\t0.0099 secs\n  Requests/sec:\t2999.8263\n\n  Total data:\t702.93 KiB\n  Size/request:\t8 B\n  Size/sec:\t23.43 KiB\n\nResponse time histogram:\n  0.005 [1]     |\n  0.026 [88299] |\u25a0\u25a0\u25a0\u25a0\u25a0\u25a0\u25a0\u25a0\u25a0\u25a0\u25a0\u25a0\u25a0\u25a0\u25a0\u25a0\u25a0\u25a0\u25a0\u25a0\u25a0\u25a0\u25a0\u25a0\u25a0\u25a0\u25a0\u25a0\u25a0\u25a0\u25a0\u25a0\n  0.047 [193]   |\n  0.068 [174]   |\n  0.089 [163]   |\n  0.110 [201]   |\n  0.132 [170]   |\n  0.153 [213]   |\n  0.174 [259]   |\n  0.195 [287]   |\n  0.216 [15]    |\n\nResponse time distribution:\n  10.00% in 0.0062 secs\n  25.00% in 0.0066 secs\n  50.00% in 0.0074 secs\n  75.00% in 0.0086 secs\n  90.00% in 0.0103 secs\n  95.00% in 0.0122 secs\n  99.00% in 0.1161 secs\n  99.90% in 0.1831 secs\n  99.99% in 0.2008 secs\n\n\nDetails (average, fastest, slowest):\n  DNS+dialup:\t0.0003 secs, 0.0001 secs, 0.0077 secs\n  DNS-lookup:\t0.0000 secs, 0.0000 secs, 0.0004 secs\n\nStatus code distribution:\n  [200] 89975 responses\n\nError distribution:\n  [25] aborted due to deadline",
    "throughput": 2999.8263
  },
  "4500": {
    "raw": "Summary:\n  Success rate:\t100.00%\n  Total:\t30.0021 secs\n  Slowest:\t0.3955 secs\n  Fastest:\t0.0048 secs\n  Average:\t0.1440 secs\n  Requests/sec:\t4495.4810\n\n  Total data:\t1.03 MiB\n  Size/request:\t8 B\n  Size/sec:\t35.11 KiB\n\nResponse time histogram:\n  0.005 [1]     |\n  0.044 [32898] |\u25a0\u25a0\u25a0\u25a0\u25a0\u25a0\u25a0\u25a0\u25a0\u25a0\u25a0\u25a0\u25a0\u25a0\u25a0\u25a0\u25a0\u25a0\u25a0\u25a0\u25a0\u25a0\u25a0\u25a0\u25a0\u25a0\u25a0\u25a0\u25a0\u25a0\u25a0\u25a0\n  0.083 [26388] |\u25a0\u25a0\u25a0\u25a0\u25a0\u25a0\u25a0\u25a0\u25a0\u25a0\u25a0\u25a0\u25a0\u25a0\u25a0\u25a0\u25a0\u25a0\u25a0\u25a0\u25a0\u25a0\u25a0\u25a0\u25a0\n  0.122 [15336] |\u25a0\u25a0\u25a0\u25a0\u25a0\u25a0\u25a0\u25a0\u25a0\u25a0\u25a0\u25a0\u25a0\u25a0\n  0.161 [7915]  |\u25a0\u25a0\u25a0\u25a0\u25a0\u25a0\u25a0\n  0.200 [9946]  |\u25a0\u25a0\u25a0\u25a0\u25a0\u25a0\u25a0\u25a0\u25a0\n  0.239 [7573]  |\u25a0\u25a0\u25a0\u25a0\u25a0\u25a0\u25a0\n  0.278 [10991] |\u25a0\u25a0\u25a0\u25a0\u25a0\u25a0\u25a0\u25a0\u25a0\u25a0\n  0.317 [4069]  |\u25a0\u25a0\u25a0\n  0.356 [12685] |\u25a0\u25a0\u25a0\u25a0\u25a0\u25a0\u25a0\u25a0\u25a0\u25a0\u25a0\u25a0\n  0.396 [7026]  |\u25a0\u25a0\u25a0\u25a0\u25a0\u25a0\n\nResponse time distribution:\n  10.00% in 0.0214 secs\n  25.00% in 0.0450 secs\n  50.00% in 0.0986 secs\n  75.00% in 0.2424 secs\n  90.00% in 0.3351 secs\n  95.00% in 0.3572 secs\n  99.00% in 0.3768 secs\n  99.90% in 0.3854 secs\n  99.99% in 0.3898 secs\n\n\nDetails (average, fastest, slowest):\n  DNS+dialup:\t0.0002 secs, 0.0001 secs, 0.0193 secs\n  DNS-lookup:\t0.0000 secs, 0.0000 secs, 0.0004 secs\n\nStatus code distribution:\n  [200] 134828 responses\n\nError distribution:\n  [46] aborted due to deadline",
    "throughput": 4495.481
  },
  "5000": {
    "raw": "Summary:\n  Success rate:\t100.00%\n  Total:\t30.0012 secs\n  Slowest:\t2.7435 secs\n  Fastest:\t0.2670 secs\n  Average:\t1.5074 secs\n  Requests/sec:\t4545.6511\n\n  Total data:\t1.04 MiB\n  Size/request:\t8 B\n  Size/sec:\t35.50 KiB\n\nResponse time histogram:\n  0.267 [1]     |\n  0.515 [11841] |\u25a0\u25a0\u25a0\u25a0\u25a0\u25a0\u25a0\u25a0\u25a0\u25a0\u25a0\u25a0\u25a0\u25a0\u25a0\u25a0\u25a0\u25a0\u25a0\u25a0\u25a0\n  0.762 [12821] |\u25a0\u25a0\u25a0\u25a0\u25a0\u25a0\u25a0\u25a0\u25a0\u25a0\u25a0\u25a0\u25a0\u25a0\u25a0\u25a0\u25a0\u25a0\u25a0\u25a0\u25a0\u25a0\u25a0\n  1.010 [13212] |\u25a0\u25a0\u25a0\u25a0\u25a0\u25a0\u25a0\u25a0\u25a0\u25a0\u25a0\u25a0\u25a0\u25a0\u25a0\u25a0\u25a0\u25a0\u25a0\u25a0\u25a0\u25a0\u25a0\u25a0\n  1.258 [13715] |\u25a0\u25a0\u25a0\u25a0\u25a0\u25a0\u25a0\u25a0\u25a0\u25a0\u25a0\u25a0\u25a0\u25a0\u25a0\u25a0\u25a0\u25a0\u25a0\u25a0\u25a0\u25a0\u25a0\u25a0\u25a0\n  1.505 [14061] |\u25a0\u25a0\u25a0\u25a0\u25a0\u25a0\u25a0\u25a0\u25a0\u25a0\u25a0\u25a0\u25a0\u25a0\u25a0\u25a0\u25a0\u25a0\u25a0\u25a0\u25a0\u25a0\u25a0\u25a0\u25a0\n  1.753 [17368] |\u25a0\u25a0\u25a0\u25a0\u25a0\u25a0\u25a0\u25a0\u25a0\u25a0\u25a0\u25a0\u25a0\u25a0\u25a0\u25a0\u25a0\u25a0\u25a0\u25a0\u25a0\u25a0\u25a0\u25a0\u25a0\u25a0\u25a0\u25a0\u25a0\u25a0\u25a0\u25a0\n  2.001 [17002] |\u25a0\u25a0\u25a0\u25a0\u25a0\u25a0\u25a0\u25a0\u25a0\u25a0\u25a0\u25a0\u25a0\u25a0\u25a0\u25a0\u25a0\u25a0\u25a0\u25a0\u25a0\u25a0\u25a0\u25a0\u25a0\u25a0\u25a0\u25a0\u25a0\u25a0\u25a0\n  2.248 [13340] |\u25a0\u25a0\u25a0\u25a0\u25a0\u25a0\u25a0\u25a0\u25a0\u25a0\u25a0\u25a0\u25a0\u25a0\u25a0\u25a0\u25a0\u25a0\u25a0\u25a0\u25a0\u25a0\u25a0\u25a0\n  2.496 [10728] |\u25a0\u25a0\u25a0\u25a0\u25a0\u25a0\u25a0\u25a0\u25a0\u25a0\u25a0\u25a0\u25a0\u25a0\u25a0\u25a0\u25a0\u25a0\u25a0\n  2.743 [12237] |\u25a0\u25a0\u25a0\u25a0\u25a0\u25a0\u25a0\u25a0\u25a0\u25a0\u25a0\u25a0\u25a0\u25a0\u25a0\u25a0\u25a0\u25a0\u25a0\u25a0\u25a0\u25a0\n\nResponse time distribution:\n  10.00% in 0.5468 secs\n  25.00% in 0.9219 secs\n  50.00% in 1.5599 secs\n  75.00% in 2.0472 secs\n  90.00% in 2.4619 secs\n  95.00% in 2.5826 secs\n  99.00% in 2.7164 secs\n  99.90% in 2.7339 secs\n  99.99% in 2.7396 secs\n\n\nDetails (average, fastest, slowest):\n  DNS+dialup:\t0.0002 secs, 0.0001 secs, 0.0136 secs\n  DNS-lookup:\t0.0000 secs, 0.0000 secs, 0.0004 secs\n\nStatus code distribution:\n  [200] 136326 responses\n\nError distribution:\n  [49] aborted due to deadline",
    "throughput": 4545.6511
  },
  "5500": {
    "raw": "Summary:\n  Success rate:\t100.00%\n  Total:\t30.0021 secs\n  Slowest:\t5.1317 secs\n  Fastest:\t0.1112 secs\n  Average:\t2.6637 secs\n  Requests/sec:\t4561.9156\n\n  Total data:\t1.04 MiB\n  Size/request:\t8 B\n  Size/sec:\t35.63 KiB\n\nResponse time histogram:\n  0.111 [1]     |\n  0.613 [13255] |\u25a0\u25a0\u25a0\u25a0\u25a0\u25a0\u25a0\u25a0\u25a0\u25a0\u25a0\u25a0\u25a0\u25a0\u25a0\u25a0\u25a0\u25a0\u25a0\u25a0\u25a0\u25a0\u25a0\u25a0\u25a0\n  1.115 [12141] |\u25a0\u25a0\u25a0\u25a0\u25a0\u25a0\u25a0\u25a0\u25a0\u25a0\u25a0\u25a0\u25a0\u25a0\u25a0\u25a0\u25a0\u25a0\u25a0\u25a0\u25a0\u25a0\u25a0\n  1.617 [14473] |\u25a0\u25a0\u25a0\u25a0\u25a0\u25a0\u25a0\u25a0\u25a0\u25a0\u25a0\u25a0\u25a0\u25a0\u25a0\u25a0\u25a0\u25a0\u25a0\u25a0\u25a0\u25a0\u25a0\u25a0\u25a0\u25a0\u25a0\u25a0\n  2.119 [13705] |\u25a0\u25a0\u25a0\u25a0\u25a0\u25a0\u25a0\u25a0\u25a0\u25a0\u25a0\u25a0\u25a0\u25a0\u25a0\u25a0\u25a0\u25a0\u25a0\u25a0\u25a0\u25a0\u25a0\u25a0\u25a0\u25a0\n  2.621 [13824] |\u25a0\u25a0\u25a0\u25a0\u25a0\u25a0\u25a0\u25a0\u25a0\u25a0\u25a0\u25a0\u25a0\u25a0\u25a0\u25a0\u25a0\u25a0\u25a0\u25a0\u25a0\u25a0\u25a0\u25a0\u25a0\u25a0\n  3.124 [12469] |\u25a0\u25a0\u25a0\u25a0\u25a0\u25a0\u25a0\u25a0\u25a0\u25a0\u25a0\u25a0\u25a0\u25a0\u25a0\u25a0\u25a0\u25a0\u25a0\u25a0\u25a0\u25a0\u25a0\u25a0\n  3.626 [16435] |\u25a0\u25a0\u25a0\u25a0\u25a0\u25a0\u25a0\u25a0\u25a0\u25a0\u25a0\u25a0\u25a0\u25a0\u25a0\u25a0\u25a0\u25a0\u25a0\u25a0\u25a0\u25a0\u25a0\u25a0\u25a0\u25a0\u25a0\u25a0\u25a0\u25a0\u25a0\u25a0\n  4.128 [11844] |\u25a0\u25a0\u25a0\u25a0\u25a0\u25a0\u25a0\u25a0\u25a0\u25a0\u25a0\u25a0\u25a0\u25a0\u25a0\u25a0\u25a0\u25a0\u25a0\u25a0\u25a0\u25a0\u25a0\n  4.630 [14347] |\u25a0\u25a0\u25a0\u25a0\u25a0\u25a0\u25a0\u25a0\u25a0\u25a0\u25a0\u25a0\u25a0\u25a0\u25a0\u25a0\u25a0\u25a0\u25a0\u25a0\u25a0\u25a0\u25a0\u25a0\u25a0\u25a0\u25a0\n  5.132 [14326] |\u25a0\u25a0\u25a0\u25a0\u25a0\u25a0\u25a0\u25a0\u25a0\u25a0\u25a0\u25a0\u25a0\u25a0\u25a0\u25a0\u25a0\u25a0\u25a0\u25a0\u25a0\u25a0\u25a0\u25a0\u25a0\u25a0\u25a0\n\nResponse time distribution:\n  10.00% in 0.6271 secs\n  25.00% in 1.4173 secs\n  50.00% in 2.6750 secs\n  75.00% in 3.8858 secs\n  90.00% in 4.6488 secs\n  95.00% in 4.8809 secs\n  99.00% in 5.0966 secs\n  99.90% in 5.1243 secs\n  99.99% in 5.1272 secs\n\n\nDetails (average, fastest, slowest):\n  DNS+dialup:\t0.0002 secs, 0.0001 secs, 0.0153 secs\n  DNS-lookup:\t0.0000 secs, 0.0000 secs, 0.0005 secs\n\nStatus code distribution:\n  [200] 136820 responses\n\nError distribution:\n  [47] aborted due to deadline",
    "throughput": 4561.9156
  },
  "6000": {
    "raw": "Summary:\n  Success rate:\t100.00%\n  Total:\t30.0016 secs\n  Slowest:\t7.3759 secs\n  Fastest:\t0.1168 secs\n  Average:\t3.7918 secs\n  Requests/sec:\t4526.9214\n\n  Total data:\t1.04 MiB\n  Size/request:\t8 B\n  Size/sec:\t35.35 KiB\n\nResponse time histogram:\n  0.117 [1]     |\n  0.843 [11837] |\u25a0\u25a0\u25a0\u25a0\u25a0\u25a0\u25a0\u25a0\u25a0\u25a0\u25a0\u25a0\u25a0\u25a0\u25a0\u25a0\u25a0\u25a0\u25a0\u25a0\u25a0\u25a0\u25a0\u25a0\u25a0\n  1.569 [14851] |\u25a0\u25a0\u25a0\u25a0\u25a0\u25a0\u25a0\u25a0\u25a0\u25a0\u25a0\u25a0\u25a0\u25a0\u25a0\u25a0\u25a0\u25a0\u25a0\u25a0\u25a0\u25a0\u25a0\u25a0\u25a0\u25a0\u25a0\u25a0\u25a0\u25a0\u25a0\n  2.295 [11831] |\u25a0\u25a0\u25a0\u25a0\u25a0\u25a0\u25a0\u25a0\u25a0\u25a0\u25a0\u25a0\u25a0\u25a0\u25a0\u25a0\u25a0\u25a0\u25a0\u25a0\u25a0\u25a0\u25a0\u25a0\u25a0\n  3.020 [13709] |\u25a0\u25a0\u25a0\u25a0\u25a0\u25a0\u25a0\u25a0\u25a0\u25a0\u25a0\u25a0\u25a0\u25a0\u25a0\u25a0\u25a0\u25a0\u25a0\u25a0\u25a0\u25a0\u25a0\u25a0\u25a0\u25a0\u25a0\u25a0\u25a0\n  3.746 [13794] |\u25a0\u25a0\u25a0\u25a0\u25a0\u25a0\u25a0\u25a0\u25a0\u25a0\u25a0\u25a0\u25a0\u25a0\u25a0\u25a0\u25a0\u25a0\u25a0\u25a0\u25a0\u25a0\u25a0\u25a0\u25a0\u25a0\u25a0\u25a0\u25a0\n  4.472 [14798] |\u25a0\u25a0\u25a0\u25a0\u25a0\u25a0\u25a0\u25a0\u25a0\u25a0\u25a0\u25a0\u25a0\u25a0\u25a0\u25a0\u25a0\u25a0\u25a0\u25a0\u25a0\u25a0\u25a0\u25a0\u25a0\u25a0\u25a0\u25a0\u25a0\u25a0\u25a0\n  5.198 [13265] |\u25a0\u25a0\u25a0\u25a0\u25a0\u25a0\u25a0\u25a0\u25a0\u25a0\u25a0\u25a0\u25a0\u25a0\u25a0\u25a0\u25a0\u25a0\u25a0\u25a0\u25a0\u25a0\u25a0\u25a0\u25a0\u25a0\u25a0\u25a0\n  5.924 [14390] |\u25a0\u25a0\u25a0\u25a0\u25a0\u25a0\u25a0\u25a0\u25a0\u25a0\u25a0\u25a0\u25a0\u25a0\u25a0\u25a0\u25a0\u25a0\u25a0\u25a0\u25a0\u25a0\u25a0\u25a0\u25a0\u25a0\u25a0\u25a0\u25a0\u25a0\n  6.650 [14947] |\u25a0\u25a0\u25a0\u25a0\u25a0\u25a0\u25a0\u25a0\u25a0\u25a0\u25a0\u25a0\u25a0\u25a0\u25a0\u25a0\u25a0\u25a0\u25a0\u25a0\u25a0\u25a0\u25a0\u25a0\u25a0\u25a0\u25a0\u25a0\u25a0\u25a0\u25a0\u25a0\n  7.376 [12344] |\u25a0\u25a0\u25a0\u25a0\u25a0\u25a0\u25a0\u25a0\u25a0\u25a0\u25a0\u25a0\u25a0\u25a0\u25a0\u25a0\u25a0\u25a0\u25a0\u25a0\u25a0\u25a0\u25a0\u25a0\u25a0\u25a0\n\nResponse time distribution:\n  10.00% in 0.9501 secs\n  25.00% in 2.0049 secs\n  50.00% in 3.8385 secs\n  75.00% in 5.5925 secs\n  90.00% in 6.5967 secs\n  95.00% in 6.9826 secs\n  99.00% in 7.3096 secs\n  99.90% in 7.3645 secs\n  99.99% in 7.3724 secs\n\n\nDetails (average, fastest, slowest):\n  DNS+dialup:\t0.0002 secs, 0.0001 secs, 0.0146 secs\n  DNS-lookup:\t0.0000 secs, 0.0000 secs, 0.0004 secs\n\nStatus code distribution:\n  [200] 135767 responses\n\nError distribution:\n  [48] aborted due to deadline",
    "throughput": 4526.9214
  }
}